napari_intensity_plotter/__init__.py
napari_intensity_plotter/_version.py
napari_intensity_plotter/_widget.py
napari_intensity_plotter/napari.yaml
napari_intensity_plotter/_tests/__init__.py
napari_intensity_plotter/_tests/test_widget.py
napari_intensity_plotter-0.1.6.dist-info/LICENSE
napari_intensity_plotter-0.1.6.dist-info/METADATA
napari_intensity_plotter-0.1.6.dist-info/WHEEL
napari_intensity_plotter-0.1.6.dist-info/entry_points.txt
napari_intensity_plotter-0.1.6.dist-info/top_level.txt
napari_intensity_plotter-0.1.6.dist-info/RECORD
