Metadata-Version: 2.1
Name: napari-intensity-plotter
Version: 0.1.6
Summary: A plugin for plotting intensity profiles with control features in napari.
Author: Toranosuke Takagi
Author-email: toranporin_1224@yahoo.co.jp
License: 
Project-URL: Bug Tracker, https://github.com/Tbrn1103/napari-intensity-plotter/issues
Project-URL: Documentation, https://github.com/Tbrn1103/napari-intensity-plotter#README.md
Project-URL: Source Code, https://github.com/Tbrn1103/napari-intensity-plotter
Project-URL: User Support, https://github.com/Tbrn1103/napari-intensity-plotter/issues
Classifier: Development Status :: 2 - Pre-Alpha
Classifier: Framework :: napari
Classifier: Intended Audience :: Developers
Classifier: License :: OSI Approved :: BSD License
Classifier: Operating System :: OS Independent
Classifier: Programming Language :: Python
Classifier: Programming Language :: Python :: 3
Classifier: Programming Language :: Python :: 3 :: Only
Classifier: Programming Language :: Python :: 3.9
Classifier: Programming Language :: Python :: 3.10
Classifier: Programming Language :: Python :: 3.11
Classifier: Programming Language :: Python :: 3.12
Classifier: Topic :: Scientific/Engineering :: Image Processing
Requires-Python: >=3.9
License-File: LICENSE
Requires-Dist: numpy
Requires-Dist: magicgui
Requires-Dist: qtpy
Requires-Dist: scikit-image
Provides-Extra: testing
Requires-Dist: tox; extra == "testing"
Requires-Dist: pytest; extra == "testing"
Requires-Dist: pytest-cov; extra == "testing"
Requires-Dist: pytest-qt; extra == "testing"
Requires-Dist: napari; extra == "testing"
Requires-Dist: pyqt5; extra == "testing"
Requires-Dist: pyqtgraph; extra == "testing"
